arbitron/__init__.py
arbitron/competition.py
arbitron/juror.py
arbitron/models.py
arbitron/pairing.py
arbitron/runner.py
arbitron-0.5.6.dist-info/WHEEL
arbitron-0.5.6.dist-info/METADATA
arbitron-0.5.6.dist-info/RECORD
