Metadata-Version: 2.3
Name: arbitron
Version: 0.5.6
Summary: Multi-agent collaboration through pairwise comparisons
Author: David Gasquez
Author-email: David Gasquez <davidgasquez@gmail.com>
Requires-Dist: pydantic-ai>=1.2.1
Requires-Python: >=3.13
